conf/__init__.py
uw_person_client/__init__.py
uw_person_client/components.py
uw_person_client/exceptions.py
uw_person_client/test.py
uw_person_client/clients/__init__.py
uw_person_client/clients/core_client.py
uw_person_client/clients/mock_client.py
uw_person_client/databases/__init__.py
uw_person_client/databases/postgres.py
uw_person_client/databases/uwpds.py
uw_person_client/fixtures/employees/bill_FBB38FE46A7C11D5A4AE0004AC494FFE_123456782.json
uw_person_client/fixtures/employees/advisers/jadviser_5136CCB9F66711D5BE060004AC494FF0_815006310.json
uw_person_client/fixtures/students/javerage_9136CCB8F66711D5BE060004AC494FFE_1033334_532353230.json
uw_person_client/fixtures/students/jbothell_FE36CCB8F66711D5BE060004AC494FCD_1233334_8205.json
uw_person_client/tests/__init__.py
uw_person_client/tests/test_components.py
uw_person_client/tests/test_core_client.py
uw_person_client/tests/test_mock_client.py
uw_person_client-2.0.2.dist-info/LICENSE
uw_person_client-2.0.2.dist-info/METADATA
uw_person_client-2.0.2.dist-info/WHEEL
uw_person_client-2.0.2.dist-info/top_level.txt
uw_person_client-2.0.2.dist-info/RECORD
