Metadata-Version: 2.1
Name: uw-person-client
Version: 2.0.2
Summary: A library for connecting to and querying the T&LS UW person datastore
Home-page: https://github.com/uw-it-aca/uw-person-client
Author: UW-IT T&LS
Author-email: aca-it@uw.edu
License: Apache License, Version 2.0
Classifier: Intended Audience :: Developers
Classifier: License :: OSI Approved :: Apache Software License
Classifier: Operating System :: OS Independent
Classifier: Programming Language :: Python
License-File: LICENSE
Requires-Dist: commonconf
Requires-Dist: mock
Requires-Dist: psycopg2-binary
Requires-Dist: SQLAlchemy ~=2.0
